ab/plot/__init__.py
ab/plot/export.py
ab/plot/util/Const.py
ab/plot/util/__init__.py
ab/plot/util/fetch_data.py
ab/plot/util/filter_raw_data.py
ab/plot/util/generate_plots.py
ab/plot/util/process_data.py
ab/plot/xls/__init__.py
ab/plot/xls/export_excel.py
ab/plot/xls/export_raw_excel.py
nn_plots-1.0.2.dist-info/LICENSE.md
nn_plots-1.0.2.dist-info/METADATA
nn_plots-1.0.2.dist-info/WHEEL
nn_plots-1.0.2.dist-info/top_level.txt
nn_plots-1.0.2.dist-info/RECORD
