Metadata-Version: 2.2
Name: nn-plots
Version: 1.0.2
Summary: Neural Network Performance Analysis
Home-page: https://github.com/ABrain-One/nn-plots
Author: ABrain One and contributors
Author-email: AI@ABrain.one
Classifier: Programming Language :: Python :: 3
Classifier: License :: OSI Approved :: MIT License
Classifier: Operating System :: OS Independent
Requires-Python: >=3.10
License-File: LICENSE.md
Requires-Dist: openpyxl
Requires-Dist: matplotlib
Requires-Dist: pandas
Requires-Dist: numpy
Requires-Dist: seaborn
Dynamic: author
Dynamic: author-email
Dynamic: classifier
Dynamic: description
Dynamic: description-content-type
Dynamic: home-page
Dynamic: requires-dist
Dynamic: requires-python
Dynamic: summary
